{
 "list": [
   {
     "id": 0,
     "title": "这是一道单选题",
     "A": "dfsa",
     "B": "fasdf",
     "C": "daffg",
     "D": "dsa"
   },
   {
     "id": 1,
     "title": "这是一道单选题",
     "A": "dfsa",
     "B": "fasdf",
     "C": "daffg",
     "D": "dsa"
   },
   {
     "id": 2,
     "title": "这是一道单选题",
     "A": "dfsa",
     "B": "fasdf",
     "C": "daffg",
     "D": "dsa"
   },
   {
     "id": 3,
     "title": "这是一道单选题",
     "A": "dfsa",
     "B": "fasdf",
     "C": "daffg",
     "D": "dsa"
   },
   {
     "id": 4,
     "title": "这是一道单选题",
     "A": "dfsa",
     "B": "fasdf",
     "C": "daffg",
     "D": "dsa"
   },
   {
     "id": 5,
     "title": "这是一道单选题",
     "A": "dfsa",
     "B": "fasdf",
     "C": "daffg",
     "D": "dsa"
   }
 ]
}
